aws_rds-0.0.2.data/scripts/aws-rds
awsrds/__init__.py
aws_rds-0.0.2.dist-info/LICENSE
aws_rds-0.0.2.dist-info/METADATA
aws_rds-0.0.2.dist-info/WHEEL
aws_rds-0.0.2.dist-info/entry_points.txt
aws_rds-0.0.2.dist-info/top_level.txt
aws_rds-0.0.2.dist-info/RECORD
