Metadata-Version: 2.1
Name: aws-rds
Version: 0.0.2
Summary: Manage AWS RDS tokens
Home-page: https://github.com/gigitsu/aws-rds
Author: Luigi Clemente
Author-email: luigi.clemente@gsquare.it
License: MIT
Keywords: aws rds db auth token db_auth_token generate_db_auth_token
Platform: UNKNOWN
Classifier: Development Status :: 5 - Production/Stable
Classifier: Intended Audience :: Developers
Classifier: Intended Audience :: System Administrators
Classifier: Topic :: System :: Systems Administration :: Authentication/Directory
Classifier: License :: OSI Approved :: MIT License
Classifier: Programming Language :: Python :: 2.7
Classifier: Programming Language :: Python :: 3.5
Classifier: Programming Language :: Python :: 3.6
Classifier: Programming Language :: Python :: 3.7
Classifier: Programming Language :: Python :: 3.8
Requires-Dist: boto3
Requires-Dist: pyperclip
